electus/__init__.py
electus/alert.py
electus/combinations.py
electus/config.py
electus/library.py
electus/main.py
electus-0.2.2.dist-info/DESCRIPTION.rst
electus-0.2.2.dist-info/METADATA
electus-0.2.2.dist-info/RECORD
electus-0.2.2.dist-info/WHEEL
electus-0.2.2.dist-info/metadata.json
electus-0.2.2.dist-info/top_level.txt
