Metadata-Version: 2.0
Name: electus
Version: 0.2.2
Summary: An engine for combining weak indicators into robust behavioural signatures
Home-page: https://gitlab.com/gclenden/electus
Author: Graham Clendenning
Author-email: graham.clendenning@uoit.net
License: MIT
Project-URL: Documentation, http://electus.readthedocs.io/en/latest/
Project-URL: Source, https://gitlab.com/gclenden/electus
Project-URL: Issue tracker, https://gitlab.com/gclenden/electus/issues
Platform: UNKNOWN
Classifier: Natural Language :: English
Classifier: Development Status :: 4 - Beta
Classifier: License :: OSI Approved :: MIT License
Classifier: Operating System :: OS Independent
Classifier: Programming Language :: Python
Classifier: Programming Language :: Python :: 3
Classifier: Programming Language :: Python :: 3.4
Classifier: Programming Language :: Python :: 3.5
Classifier: Programming Language :: Python :: 3.6
Requires-Dist: python-dateutil
Requires-Dist: boolean.py
Requires-Dist: pytest
Requires-Dist: requests
